{
	"name": "Default bindings for Vive Trackers",
	"controller_type": "vive_tracker_camera",
	"last_edited_by": "UnrealEngine",
	"bindings":
	{
		"/actions/main":
		{
			"sources": [
				{
					"mode": "button",
					"path": "/user/hand/left/input/application_menu",
					"inputs":
					{
						"click":
						{
							"output": "/actions/main/in/Menu_L"
						}
					}
				},
				{
					"mode": "trigger",
					"path": "/user/hand/left/input/trigger",
					"inputs":
					{
						"click":
						{
							"output": "/actions/main/in/Trigger_L"
						}
					}
				},
				{
					"mode": "button",
					"path": "/user/hand/left/input/grip",
					"inputs":
					{
						"click":
						{
							"output": "/actions/main/in/Grip_L"
						}
					}
				},
				{
					"mode": "trackpad",
					"path": "/user/hand/left/input/trackpad",
					"inputs":
					{
						"touch":
						{
							"output": "/actions/main/in/PadCap_L"
						}
					}
				},
				{
					"mode": "trackpad",
					"path": "/user/hand/left/input/trackpad",
					"inputs":
					{
						"click":
						{
							"output": "/actions/main/in/Trackpad_L"
						}
					}
				},
				{
					"mode": "dpad",
					"path": "/user/hand/left/input/trackpad",
					"parameters":
					{
						"sub_mode": "click"
					},
					"inputs":
					{
						"north":
						{
							"output": "/actions/main/in/TrackpadUp_L"
						}
					}
				},
				{
					"mode": "dpad",
					"path": "/user/hand/left/input/trackpad",
					"parameters":
					{
						"sub_mode": "click"
					},
					"inputs":
					{
						"south":
						{
							"output": "/actions/main/in/TrackpadDown_L"
						}
					}
				},
				{
					"mode": "dpad",
					"path": "/user/hand/left/input/trackpad",
					"parameters":
					{
						"sub_mode": "click"
					},
					"inputs":
					{
						"west":
						{
							"output": "/actions/main/in/TrackpadLeft_L"
						}
					}
				},
				{
					"mode": "dpad",
					"path": "/user/hand/left/input/trackpad",
					"parameters":
					{
						"sub_mode": "click"
					},
					"inputs":
					{
						"east":
						{
							"output": "/actions/main/in/TrackpadRight_L"
						}
					}
				},
				{
					"mode": "button",
					"path": "/user/hand/right/input/application_menu",
					"inputs":
					{
						"click":
						{
							"output": "/actions/main/in/Menu_R"
						}
					}
				},
				{
					"mode": "trigger",
					"path": "/user/hand/right/input/trigger",
					"inputs":
					{
						"click":
						{
							"output": "/actions/main/in/Trigger_R"
						}
					}
				},
				{
					"mode": "button",
					"path": "/user/hand/right/input/grip",
					"inputs":
					{
						"click":
						{
							"output": "/actions/main/in/Grip_R"
						}
					}
				},
				{
					"mode": "trackpad",
					"path": "/user/hand/right/input/trackpad",
					"inputs":
					{
						"touch":
						{
							"output": "/actions/main/in/PadCap_R"
						}
					}
				},
				{
					"mode": "trackpad",
					"path": "/user/hand/right/input/trackpad",
					"inputs":
					{
						"click":
						{
							"output": "/actions/main/in/Trackpad_R"
						}
					}
				},
				{
					"mode": "dpad",
					"path": "/user/hand/right/input/trackpad",
					"parameters":
					{
						"sub_mode": "click"
					},
					"inputs":
					{
						"north":
						{
							"output": "/actions/main/in/TrackpadUp_R"
						}
					}
				},
				{
					"mode": "dpad",
					"path": "/user/hand/right/input/trackpad",
					"parameters":
					{
						"sub_mode": "click"
					},
					"inputs":
					{
						"south":
						{
							"output": "/actions/main/in/TrackpadDown_R"
						}
					}
				},
				{
					"mode": "dpad",
					"path": "/user/hand/right/input/trackpad",
					"parameters":
					{
						"sub_mode": "click"
					},
					"inputs":
					{
						"west":
						{
							"output": "/actions/main/in/TrackpadLeft_R"
						}
					}
				},
				{
					"mode": "dpad",
					"path": "/user/hand/right/input/trackpad",
					"parameters":
					{
						"sub_mode": "click"
					},
					"inputs":
					{
						"east":
						{
							"output": "/actions/main/in/TrackpadRight_R"
						}
					}
				},
				{
					"mode": "dpad",
					"path": "/user/hand/left/input/trackpad",
					"parameters":
					{
						"sub_mode": "click"
					},
					"inputs":
					{
						"north":
						{
							"output": "/actions/main/in/Teleport_L"
						}
					}
				},
				{
					"mode": "dpad",
					"path": "/user/hand/right/input/trackpad",
					"parameters":
					{
						"sub_mode": "click"
					},
					"inputs":
					{
						"north":
						{
							"output": "/actions/main/in/Teleport_R"
						}
					}
				},
				{
					"mode": "button",
					"path": "/user/hand/left/input/grip",
					"inputs":
					{
						"click":
						{
							"output": "/actions/main/in/Emote_L"
						}
					}
				},
				{
					"mode": "button",
					"path": "/user/hand/right/input/grip",
					"inputs":
					{
						"click":
						{
							"output": "/actions/main/in/Emote_R"
						}
					}
				},
				{
					"mode": "dpad",
					"path": "/user/hand/left/input/trackpad",
					"parameters":
					{
						"sub_mode": "click"
					},
					"inputs":
					{
						"south":
						{
							"output": "/actions/main/in/Console"
						}
					}
				},
				{
					"mode": "trigger",
					"path": "/user/hand/left/input/trigger",
					"inputs":
					{
						"click":
						{
							"output": "/actions/main/in/Interact_L"
						}
					}
				},
				{
					"mode": "trigger",
					"path": "/user/hand/right/input/trigger",
					"inputs":
					{
						"click":
						{
							"output": "/actions/main/in/Interact_R"
						}
					}
				},
				{
					"mode": "trigger",
					"path": "/user/hand/left/input/trigger",
					"inputs":
					{
						"pull":
						{
							"output": "/actions/main/in/TriggerAxis_L axis"
						}
					}
				},
				{
					"mode": "scalar_constant",
					"path": "/user/hand/left/input/grip",
					"inputs":
					{
						"value":
						{
							"output": "/actions/main/in/GripAxis_L axis"
						}
					}
				},
				{
					"mode": "trackpad",
					"path": "/user/hand/left/input/trackpad",
					"inputs":
					{
						"position":
						{
							"output": "/actions/main/in/PadL_X,PadL_Y X Y_axis2d"
						}
					}
				},
				{
					"mode": "trigger",
					"path": "/user/hand/right/input/trigger",
					"inputs":
					{
						"pull":
						{
							"output": "/actions/main/in/TriggerAxis_R axis"
						}
					}
				},
				{
					"mode": "scalar_constant",
					"path": "/user/hand/right/input/grip",
					"inputs":
					{
						"value":
						{
							"output": "/actions/main/in/GripAxis_R axis"
						}
					}
				},
				{
					"mode": "trackpad",
					"path": "/user/hand/right/input/trackpad",
					"inputs":
					{
						"position":
						{
							"output": "/actions/main/in/PadR_X,PadR_Y X Y_axis2d"
						}
					}
				}
			],
			"poses": [
				{
					"output": "/actions/main/in/special1",
					"path": "/user/hand/left/pose/back",
					"requirement": "optional"
				},
				{
					"output": "/actions/main/in/special2",
					"path": "/user/hand/right/pose/back",
					"requirement": "optional"
				},
				{
					"output": "/actions/main/in/special3",
					"path": "/user/hand/left/pose/front",
					"requirement": "optional"
				},
				{
					"output": "/actions/main/in/special4",
					"path": "/user/hand/right/pose/front",
					"requirement": "optional"
				},
				{
					"output": "/actions/main/in/special5",
					"path": "/user/hand/left/pose/frontandrolled",
					"requirement": "optional"
				},
				{
					"output": "/actions/main/in/special6",
					"path": "/user/hand/right/pose/frontandrolled",
					"requirement": "optional"
				},
				{
					"output": "/actions/main/in/special7",
					"path": "/user/hand/left/pose/pistolgrip",
					"requirement": "optional"
				},
				{
					"output": "/actions/main/in/special8",
					"path": "/user/hand/right/pose/pistolgrip",
					"requirement": "optional"
				}
			]
		}
	},
	"description": "VR Immersive Hands-11590370"
}